{
  "location": {
    "name": "New York",
    "region": "New York",
    "country": "United States of America",
    "lat": 40.7142,
    "lon": -74.0064,
    "tz_id": "America/New_York",
    "localtime_epoch": 1742102279,
    "localtime": "2025-03-16 01:17"
  },
  "current": {
    "last_updated_epoch": 1742102100,
    "last_updated": "2025-03-16 01:15",
    "temp_c": 8.9,
    "temp_f": 48,
    "is_day": 0,
    "condition": {
      "text": "Mist",
      "icon": "//cdn.weatherapi.com/weather/64x64/night/143.png",
      "code": 1030
    },
    "wind_mph": 4.9,
    "wind_kph": 7.9,
    "wind_degree": 177,
    "wind_dir": "S",
    "pressure_mb": 1019,
    "pressure_in": 30.09,
    "precip_mm": 0,
    "precip_in": 0,
    "humidity": 93,
    "cloud": 100,
    "feelslike_c": 7.7,
    "feelslike_f": 45.9,
    "windchill_c": 5.5,
    "windchill_f": 42,
    "heatindex_c": 7,
    "heatindex_f": 44.6,
    "dewpoint_c": 6.6,
    "dewpoint_f": 43.9,
    "vis_km": 3.2,
    "vis_miles": 1,
    "uv": 0,
    "gust_mph": 9.5,
    "gust_kph": 15.3
  }
}